pyperf/__init__.py
pyperf/__main__.py
pyperf/_bench.py
pyperf/_cli.py
pyperf/_collect_metadata.py
pyperf/_command.py
pyperf/_compare.py
pyperf/_cpu_utils.py
pyperf/_formatter.py
pyperf/_hooks.py
pyperf/_linux_memory.py
pyperf/_manager.py
pyperf/_metadata.py
pyperf/_process_time.py
pyperf/_psutil_memory.py
pyperf/_runner.py
pyperf/_system.py
pyperf/_timeit.py
pyperf/_timeit_cli.py
pyperf/_utils.py
pyperf/_win_memory.py
pyperf/_worker.py
pyperf/tests/__init__.py
pyperf/tests/mult_list_bench.py
pyperf/tests/mult_list_py36.json
pyperf/tests/mult_list_py36_tags.json
pyperf/tests/mult_list_py37.json
pyperf/tests/mult_list_py37_tags.json
pyperf/tests/mult_list_py38.json
pyperf/tests/replay.py
pyperf/tests/telco.json
pyperf/tests/test_bench.py
pyperf/tests/test_cli.py
pyperf/tests/test_examples.py
pyperf/tests/test_metadata.py
pyperf/tests/test_misc.py
pyperf/tests/test_perf_cli.py
pyperf/tests/test_runner.py
pyperf/tests/test_system.py
pyperf/tests/test_timeit.py
pyperf/tests/test_utils.py
pyperf/tests/track_memory.json
pyperf-2.8.1.dist-info/COPYING
pyperf-2.8.1.dist-info/METADATA
pyperf-2.8.1.dist-info/WHEEL
pyperf-2.8.1.dist-info/entry_points.txt
pyperf-2.8.1.dist-info/top_level.txt
pyperf-2.8.1.dist-info/RECORD
