Metadata-Version: 2.1
Name: pyperf
Version: 2.8.1
Summary: Python module to run and analyze benchmarks
Author-email: Victor Stinner <vstinner@redhat.com>
Maintainer-email: Dong-hee Na <donghee.na@python.org>
License: MIT
Project-URL: Homepage, https://github.com/psf/pyperf
Classifier: Development Status :: 5 - Production/Stable
Classifier: Intended Audience :: Developers
Classifier: License :: OSI Approved :: MIT License
Classifier: Natural Language :: English
Classifier: Operating System :: OS Independent
Classifier: Programming Language :: Python :: 3
Classifier: Topic :: Software Development :: Libraries :: Python Modules
Requires-Python: >=3.9
License-File: COPYING
Requires-Dist: psutil >=5.9.0
Provides-Extra: dev
Requires-Dist: tox ; extra == 'dev'
